newrelic_introspector/__init__.py
newrelic_introspector/__main__.py
newrelic_introspector/lsi.py
newrelic_introspector/version.py
newrelic_introspector-0.0.6.dist-info/LICENSE
newrelic_introspector-0.0.6.dist-info/METADATA
newrelic_introspector-0.0.6.dist-info/WHEEL
newrelic_introspector-0.0.6.dist-info/entry_points.txt
newrelic_introspector-0.0.6.dist-info/top_level.txt
newrelic_introspector-0.0.6.dist-info/RECORD
