Metadata-Version: 2.1
Name: newrelic-introspector
Version: 0.0.6
Summary: New Relic Python Process Introspector
Home-page: https://github.com/newrelic/newrelic-introspector-python
Author: New Relic
Author-email: open-source@newrelic.com
Maintainer: New Relic
Maintainer-email: open-source@newrelic.com
License: Apache-2.0
Project-URL: Source, https://github.com/newrelic/newrelic-introspector-python
Platform: any
Classifier: Development Status :: 3 - Alpha
Classifier: Topic :: System :: Monitoring
Classifier: Programming Language :: Python :: Implementation :: PyPy
Classifier: Programming Language :: Python :: Implementation :: CPython
Classifier: Programming Language :: Python :: 2
Classifier: Programming Language :: Python :: 2.7
Classifier: Programming Language :: Python :: 3
Classifier: Programming Language :: Python :: 3.6
Classifier: Programming Language :: Python :: 3.7
Classifier: Programming Language :: Python :: 3.8
Classifier: Programming Language :: Python :: 3.9
Classifier: Operating System :: OS Independent
Classifier: License :: OSI Approved :: Apache Software License
Requires-Python: !=3.0.*,!=3.1.*,!=3.2.*,!=3.3.*,!=3.4.*,!=3.5.*,>=2.7
License-File: LICENSE
